{"about_aboutduck.md":"6b841a57","about_aboutme.md":"9340b89c","backend_express_index.md":"ba87c13a","backend_mysql_index.md":"4b6db38a","backend_node_index.md":"feb0c67b","deploy_vitepress_ico.md":"63a87b07","frontend_css_css3_compatibility.md":"baf56ea5","frontend_css_css3_media.md":"91847565","frontend_css_css3_note.md":"e96be495","frontend_css_css3_text.md":"830ee4c1","frontend_css_css3_animation.md":"7f1555f8","frontend_css_css3_background.md":"b1322911","frontend_css_css3_transform.md":"93e90c0a","frontend_css_css3_transition.md":"2e21b1e2","frontend_css_css_codesnippet.md":"aef57b2e","frontend_css_css_note.md":"73361a59","frontend_css_css_selector.md":"b659a797","frontend_css_css_sprite.md":"64dc9818","frontend_css_layout_center.md":"1770cb38","frontend_css_layout_flex.md":"c7ea5c18","frontend_css_layout_grid.md":"a3318325","frontend_frontend_helloworld.md":"e1827905","frontend_frontend_learningpath.md":"9225cec1","frontend_frontend_weapons.md":"6ef368d6","frontend_frontend_index.md":"5fe4c368","frontend_frontend_introduce.md":"6b9dfc8f","frontend_html_html5webstorage.md":"8bc7f6a3","frontend_html_htmlnote.md":"5e6a2558","frontend_javascript_index.md":"ed5eb556","frontend_typescript_index.md":"a0b8ac03","frontend_vue_index.md":"d285b829","note_git.md":"a0069465","note_git2.md":"8927a668","note_git_remote.md":"81c3d69d","note_vscode.md":"13bc5071","note_yarn.md":"96e60bae","python_python_pythonfile.md":"0989ef64","python_python_pythonnote.md":"6df784dc","python_python_pythonnote_json.md":"5e88f310","python_python_pythonnote_withas.md":"3b347805","python_python_pythonnote_dict和set.md":"165bf1af","python_python_pythonnote_元组.md":"65864d2b","python_python_pythonnote_函数.md":"439b6dbe","python_python_pythonnote_列表生成式.md":"144585c2","python_python_pythonnote_变量.md":"0c0fff96","python_python_pythonnote_字符串.md":"1ce9b6e9","python_python_pythonnote_异常处理.md":"04aadf3b","python_python_pythonnote_循环.md":"60737684","python_python_pythonnote_数据类型.md":"83e288d5","python_python_pythonnote_数据类型转换.md":"d995b1cf","python_python_pythonnote_数组.md":"613c87b6","python_python_pythonnote_条件判断.md":"c11fdcc3","python_python_python介绍.md":"3534f3d0","python_python_python安装.md":"94679490","python_python_未完待续.md":"291c6183","python_spider_index.md":"e94d2c3c","python_sqlite_index.md":"e023b3aa","index.md":"46a9e0d0","other_style初始化.md":"364bb3e3","other_iconfont.md":"a62ee709"}
